pydantic_kms_secrets/__init__.py
pydantic_kms_secrets/cli.py
pydantic_kms_secrets/kms.py
pydantic_kms_secrets/pydantic.py
pydantic_kms_secrets-0.3.0.dist-info/LICENSE
pydantic_kms_secrets-0.3.0.dist-info/METADATA
pydantic_kms_secrets-0.3.0.dist-info/WHEEL
pydantic_kms_secrets-0.3.0.dist-info/entry_points.txt
pydantic_kms_secrets-0.3.0.dist-info/top_level.txt
pydantic_kms_secrets-0.3.0.dist-info/RECORD
