Metadata-Version: 2.1
Name: pydantic-kms-secrets
Version: 0.3.0
Summary: Utility to decrypt and encrypt secrets using AWS KMS keys that is compatible with pydantic models
Home-page: https://github.com/nplutt/pydantic-kms-secrets
Author: Nick Plutt
Author-email: nplutt@gmail.com
License: MIT
Project-URL: Source Code, https://github.com/nplutt/pydantic-kms-secrets/
Keywords: pydantic aws secrets kms secrets-management environment-variables python
Platform: UNKNOWN
Classifier: Intended Audience :: Developers
Classifier: Programming Language :: Python :: 3.6
Classifier: Programming Language :: Python :: 3.7
Classifier: Programming Language :: Python :: 3.8
Requires-Python: >=3.6
Requires-Dist: boto3
Provides-Extra: dev
Requires-Dist: black ; extra == 'dev'
Requires-Dist: isort ; extra == 'dev'
Requires-Dist: pydantic ; extra == 'dev'
Provides-Extra: test
Requires-Dist: pytest ; extra == 'test'
Requires-Dist: pytest-cov ; extra == 'test'
